[{"name":"sjds #1","description":"testing","attributes":[{"traitType":"1.png","value":""},{"traitType":"2.png","value":""},{"traitType":"a.png","value":""}]},{"name":"sjds #2","description":"testing","attributes":[{"traitType":"1.png","value":""},{"traitType":"2.png","value":""},{"traitType":"a.png","value":""}]},{"name":"sjds #3","description":"testing","attributes":[{"traitType":"1.png","value":""},{"traitType":"2.png","value":""},{"traitType":"a.png","value":""}]},{"name":"sjds #4","description":"testing","attributes":[{"traitType":"1.png","value":""},{"traitType":"2.png","value":""},{"traitType":"a.png","value":""}]}]